byteplussdkalb
byteplussdkapig
byteplussdkapig20221112
byteplussdkark
byteplussdkarkruntime
byteplussdkautoscaling
byteplussdkbilling
byteplussdkcloudmonitor
byteplussdkcore
byteplussdkcr
byteplussdkdirectconnect
byteplussdkdms
byteplussdkecopartner
byteplussdkecs
byteplussdkescloud
byteplussdkfilenas
byteplussdkiam20210801
byteplussdkkafka
byteplussdkkms
byteplussdkllmshield
byteplussdkmlplatform20240701
byteplussdknatgateway
byteplussdkquota
byteplussdkrabbitmq
byteplussdkrdsmssql
byteplussdkrdsmysqlv2
byteplussdkrdspostgresql
byteplussdkredis
byteplussdkresourceshare
byteplussdksmc
byteplussdkstorageebs
byteplussdktag
byteplussdktransitrouter
byteplussdkvedbm
byteplussdkvefaas
byteplussdkvepfs
byteplussdkvke
byteplussdkvmp
byteplussdkvod20250701
byteplussdkvpc
