Metadata-Version: 2.1
Name: byteplus-python-sdk-v2
Version: 3.0.29
Summary: Byteplus SDK for Python
License: Apache License 2.0
Platform: any
Provides-Extra: ark
License-File: LICENSE.txt
License-File: NOTICE.md
